Workbook

Sheet Assumptions
A1: EQUITY VALUATION MODEL — ASSUMPTIONS
A2: Color Code: Blue = Input | Black = Formula | Green = Cross-sheet link
A4: COMPANY INFORMATION
A5: Company Name | B5: DEMO Corp. | C5: Enter full company name
A6: Ticker Symbol | B6: DEMO | C6: Exchange:Ticker
A7: Reporting Currency | B7: USD ($M) | C7: All figures in $M unless noted
A8: Valuation Date | B8: 2024-12-31 | C8: YYYY-MM-DD
A10: CAPITAL STRUCTURE (WACC INPUTS)
A11: Risk-Free Rate (10Y Treasury) | B11: 0.04 | C11: Source: US Treasury
A12: Equity Risk Premium | B12: 0.055 | C12: Source: Damodaran (2024)
A13: Levered Beta | B13: 1.15 | C13: Source: Bloomberg LTM
A14: Pre-Tax Cost of Debt | B14: 0.045 | C14: YTM of LT debt
A15: Effective Tax Rate | B15: 0.21 | C15: Blended effective rate
A16: Debt Weight (D/V) | B16: 0.25 | C16: Market value weights
A17: Equity Weight (E/V) | B17: =1-B16 | C17: Auto-calculated
A18: Size Premium | B18: 0.01 | C18: Duff & Phelps
A19: Specific Risk Premium | B19: 0 | C19: Company-specific adj.
A21: DCF ASSUMPTIONS
A22: Projection Horizon (Years) | B22: 5
A23: LTM Revenue ($M) | B23: 12600 | C23: Most recent 12 months
A24: Terminal Growth Rate (g) | B24: 0.025 | C24: Long-run nominal growth
A25: Exit Multiple (EV/EBITDA) | B25: 12 | C25: Alt. TV method
A26: Terminal Value Method | B26: Gordon Growth | C26: Gordon Growth or Exit Multiple
A28: FCF DRIVER ASSUMPTIONS
A29: Revenue Growth — Year 1 | B29: 0.12
A30: Revenue Growth — Year 2 | B30: 0.1
A31: Revenue Growth — Year 3 | B31: 0.09
A32: Revenue Growth — Year 4 | B32: 0.08
A33: Revenue Growth — Year 5 | B33: 0.07
A34: EBITDA Margin (stable) | B34: 0.27 | C34: % of Revenue
A35: D&A (% of Revenue) | B35: 0.05
A36: CapEx (% of Revenue) | B36: 0.06
A37: Δ NWC (% of Revenue Δ) | B37: 0.015
A39: BALANCE SHEET (LTM)
A40: Total Debt ($M) | B40: 4200 | C40: Gross financial debt
A41: Cash & Equivalents ($M) | B41: 2100
A42: Net Debt ($M) | B42: =B40-B41 | C42: Auto-calculated
A43: Shares Outstanding (M) | B43: 500 | C43: Fully diluted

Sheet Income Projection
A1: INCOME STATEMENT PROJECTION
B3: Year 1 | C3: Year 2 | D3: Year 3 | E3: Year 4 | F3: Year 5
B4: FY+1 | C4: FY+2 | D4: FY+3 | E4: FY+4 | F4: FY+5
A6: Revenue ($M) | B6: =Assumptions!B23*(1+Assumptions!B29) | C6: =B6*(1+Assumptions!B30) | D6: =C6*(1+Assumptions!B31) | E6: =D6*(1+Assumptions!B32) | F6: =E6*(1+Assumptions!B33)
A7: Revenue Growth | B7: =Assumptions!B29 | C7: =C6/B6-1 | D7: =D6/C6-1 | E7: =E6/D6-1 | F7: =F6/E6-1
A8: EBITDA ($M) | B8: =B6*Assumptions!B34 | C8: =C6*Assumptions!B34 | D8: =D6*Assumptions!B34 | E8: =E6*Assumptions!B34 | F8: =F6*Assumptions!B34
A9: EBITDA Margin | B9: =B8/B6 | C9: =C8/C6 | D9: =D8/D6 | E9: =E8/E6 | F9: =F8/F6
A10: D&A ($M) | B10: =B6*Assumptions!B35 | C10: =C6*Assumptions!B35 | D10: =D6*Assumptions!B35 | E10: =E6*Assumptions!B35 | F10: =F6*Assumptions!B35
A11: EBIT ($M) | B11: =B8-B10 | C11: =C8-C10 | D11: =D8-D10 | E11: =E8-E10 | F11: =F8-F10
A12: NOPAT = EBIT × (1-T) | B12: =B12*(1-Assumptions!B15) | C12: =C12*(1-Assumptions!B15) | D12: =D12*(1-Assumptions!B15) | E12: =E12*(1-Assumptions!B15) | F12: =F12*(1-Assumptions!B15)

Sheet DCF
A1: DCF VALUATION — FREE CASH FLOW & ENTERPRISE VALUE
A3: WACC Calculation
A4: Cost of Equity (CAPM) | B4: =Assumptions!B11+Assumptions!B13*Assumptions!B12+Assumptions!B18+Assumptions!B19
A5: After-Tax Cost of Debt | B5: =Assumptions!B14*(1-Assumptions!B15)
A6: WACC | B6: =B4*Assumptions!B17+B5*Assumptions!B16
A8: Free Cash Flow Bridge
B9: Year 1 | C9: Year 2 | D9: Year 3 | E9: Year 4 | F9: Year 5
A10: NOPAT ($M) | B10: ='Income Projection'!B13 | C10: ='Income Projection'!C13 | D10: ='Income Projection'!D13 | E10: ='Income Projection'!E13 | F10: ='Income Projection'!F13
A11: + D&A ($M) | B11: ='Income Projection'!B10 | C11: ='Income Projection'!C10 | D11: ='Income Projection'!D10 | E11: ='Income Projection'!E10 | F11: ='Income Projection'!F10
A12: - CapEx ($M) | B12: =-'Income Projection'!B6*Assumptions!B36 | C12: =-'Income Projection'!C6*Assumptions!B36 | D12: =-'Income Projection'!D6*Assumptions!B36 | E12: =-'Income Projection'!E6*Assumptions!B36 | F12: =-'Income Projection'!F6*Assumptions!B36
A13: - Δ NWC ($M) | B13: =-('Income Projection'!B6-Assumptions!B23)*Assumptions!B37 | C13: =-('Income Projection'!C6-'Income Projection'!B6)*Assumptions!B37 | D13: =-('Income Projection'!D6-'Income Projection'!C6)*Assumptions!B37 | E13: =-('Income Projection'!E6-'Income Projection'!D6)*Assumptions!B37 | F13: =-('Income Projection'!F6-'Income Projection'!E6)*Assumptions!B37
A14: =Free Cash Flow ($M) | B14: =B10+B11+B12+B13 | C14: =C10+C11+C12+C13 | D14: =D10+D11+D12+D13 | E14: =E10+E11+E12+E13 | F14: =F10+F11+F12+F13
A15: Discount Factor | B15: =1/(1+$B$6)^1 | C15: =1/(1+$B$6)^2 | D15: =1/(1+$B$6)^3 | E15: =1/(1+$B$6)^4 | F15: =1/(1+$B$6)^5
A16: PV of FCF ($M) | B16: =B14*B15 | C16: =C14*C15 | D16: =D14*D15 | E16: =E14*E15 | F16: =F14*F15
A19: Enterprise Value Bridge
A20: Sum of PV(FCFs) ($M) | B20: =SUM(B16:F16)
A21: Terminal Value ($M) | B21: ='Income Projection'!F8/(DCF!B6-Assumptions!B24)*(1+Assumptions!B24)
A22: PV(Terminal Value) ($M) | B22: =B21/(1+B6)^5
A23: Enterprise Value ($M) | B23: =B20+B22
A24: (-) Net Debt ($M) | B24: =Assumptions!B42
A25: Equity Value ($M) | B25: =B23-B24
A26: Shares Outstanding (M) | B26: =Assumptions!B43
A27: Intrinsic Value per Share | B27: =B25/B26
A28: TV as % of EV | B28: =B22/B23

Sheet Sensitivity
A1: SENSITIVITY ANALYSIS — EQUITY VALUE ($M)
A3: Equity Value by WACC × Terminal Growth Rate
A4: WACC \ g | B4: 0.015 | C4: 0.02 | D4: 0.025 | E4: 0.03 | F4: 0.035
A5: 0.07 | B5: =DCF!B20 + 'Income Projection'!F8*(1+0.015)/(0.07-0.015)/(1+0.07)^5 -Assumptions!B42 | C5: =DCF!B20 + 'Income Projection'!F8*(1+0.02)/(0.07-0.02)/(1+0.07)^5 -Assumptions!B42 | D5: =DCF!B20 + 'Income Projection'!F8*(1+0.025)/(0.07-0.025)/(1+0.07)^5 -Assumptions!B42 | E5: =DCF!B20 + 'Income Projection'!F8*(1+0.03)/(0.07-0.03)/(1+0.07)^5 -Assumptions!B42 | F5: =DCF!B20 + 'Income Projection'!F8*(1+0.035)/(0.07-0.035)/(1+0.07)^5 -Assumptions!B42
A6: 0.075 | B6: =DCF!B20 + 'Income Projection'!F8*(1+0.015)/(0.075-0.015)/(1+0.075)^5 -Assumptions!B42 | C6: =DCF!B20 + 'Income Projection'!F8*(1+0.02)/(0.075-0.02)/(1+0.075)^5 -Assumptions!B42 | D6: =DCF!B20 + 'Income Projection'!F8*(1+0.025)/(0.075-0.025)/(1+0.075)^5 -Assumptions!B42 | E6: =DCF!B20 + 'Income Projection'!F8*(1+0.03)/(0.075-0.03)/(1+0.075)^5 -Assumptions!B42 | F6: =DCF!B20 + 'Income Projection'!F8*(1+0.035)/(0.075-0.035)/(1+0.075)^5 -Assumptions!B42
A7: 0.08 | B7: =DCF!B20 + 'Income Projection'!F8*(1+0.015)/(0.08-0.015)/(1+0.08)^5 -Assumptions!B42 | C7: =DCF!B20 + 'Income Projection'!F8*(1+0.02)/(0.08-0.02)/(1+0.08)^5 -Assumptions!B42 | D7: =DCF!B20 + 'Income Projection'!F8*(1+0.025)/(0.08-0.025)/(1+0.08)^5 -Assumptions!B42 | E7: =DCF!B20 + 'Income Projection'!F8*(1+0.03)/(0.08-0.03)/(1+0.08)^5 -Assumptions!B42 | F7: =DCF!B20 + 'Income Projection'!F8*(1+0.035)/(0.08-0.035)/(1+0.08)^5 -Assumptions!B42
A8: 0.085 | B8: =DCF!B20 + 'Income Projection'!F8*(1+0.015)/(0.085-0.015)/(1+0.085)^5 -Assumptions!B42 | C8: =DCF!B20 + 'Income Projection'!F8*(1+0.02)/(0.085-0.02)/(1+0.085)^5 -Assumptions!B42 | D8: =DCF!B20 + 'Income Projection'!F8*(1+0.025)/(0.085-0.025)/(1+0.085)^5 -Assumptions!B42 | E8: =DCF!B20 + 'Income Projection'!F8*(1+0.03)/(0.085-0.03)/(1+0.085)^5 -Assumptions!B42 | F8: =DCF!B20 + 'Income Projection'!F8*(1+0.035)/(0.085-0.035)/(1+0.085)^5 -Assumptions!B42
A9: 0.09 | B9: =DCF!B20 + 'Income Projection'!F8*(1+0.015)/(0.09-0.015)/(1+0.09)^5 -Assumptions!B42 | C9: =DCF!B20 + 'Income Projection'!F8*(1+0.02)/(0.09-0.02)/(1+0.09)^5 -Assumptions!B42 | D9: =DCF!B20 + 'Income Projection'!F8*(1+0.025)/(0.09-0.025)/(1+0.09)^5 -Assumptions!B42 | E9: =DCF!B20 + 'Income Projection'!F8*(1+0.03)/(0.09-0.03)/(1+0.09)^5 -Assumptions!B42 | F9: =DCF!B20 + 'Income Projection'!F8*(1+0.035)/(0.09-0.035)/(1+0.09)^5 -Assumptions!B42
A10: 0.095 | B10: =DCF!B20 + 'Income Projection'!F8*(1+0.015)/(0.095-0.015)/(1+0.095)^5 -Assumptions!B42 | C10: =DCF!B20 + 'Income Projection'!F8*(1+0.02)/(0.095-0.02)/(1+0.095)^5 -Assumptions!B42 | D10: =DCF!B20 + 'Income Projection'!F8*(1+0.025)/(0.095-0.025)/(1+0.095)^5 -Assumptions!B42 | E10: =DCF!B20 + 'Income Projection'!F8*(1+0.03)/(0.095-0.03)/(1+0.095)^5 -Assumptions!B42 | F10: =DCF!B20 + 'Income Projection'!F8*(1+0.035)/(0.095-0.035)/(1+0.095)^5 -Assumptions!B42
A11: 0.1 | B11: =DCF!B20 + 'Income Projection'!F8*(1+0.015)/(0.1-0.015)/(1+0.1)^5 -Assumptions!B42 | C11: =DCF!B20 + 'Income Projection'!F8*(1+0.02)/(0.1-0.02)/(1+0.1)^5 -Assumptions!B42 | D11: =DCF!B20 + 'Income Projection'!F8*(1+0.025)/(0.1-0.025)/(1+0.1)^5 -Assumptions!B42 | E11: =DCF!B20 + 'Income Projection'!F8*(1+0.03)/(0.1-0.03)/(1+0.1)^5 -Assumptions!B42 | F11: =DCF!B20 + 'Income Projection'!F8*(1+0.035)/(0.1-0.035)/(1+0.1)^5 -Assumptions!B42

Sheet Comps
A1: COMPARABLE COMPANY ANALYSIS — TRADING MULTIPLES
A3: Company | B3: Market Cap | C3: Net Debt | D3: EV | E3: Revenue | F3: EBITDA | G3: EV/Revenue | H3: EV/EBITDA | I3: P/E
A4: Alpha Tech | B4: 42000 | C4: 2500 | D4: =B4+C4 | E4: 12600 | F4: 3150 | G4: =D4/E4 | H4: =D4/F4
A5: Beta Systems | B5: 28000 | C5: 1200 | D5: =B5+C5 | E5: 7800 | F5: 1872 | G5: =D5/E5 | H5: =D5/F5
A6: Gamma Corp | B6: 65000 | C6: 4100 | D6: =B6+C6 | E6: 18200 | F6: 4914 | G6: =D6/E6 | H6: =D6/F6
A7: Delta Inc | B7: 19500 | C7: 800 | D7: =B7+C7 | E7: 5400 | F7: 1188 | G7: =D7/E7 | H7: =D7/F7
A8: Epsilon Ltd | B8: 35000 | C8: 2000 | D8: =B8+C8 | E8: 10500 | F8: 2625 | G8: =D8/E8 | H8: =D8/F8
A10: Mean | G10: =AVERAGE(G4:G8) | H10: =AVERAGE(H4:H8)
A11: Median | G11: =MEDIAN(G4:G8) | H11: =MEDIAN(H4:H8)
A12: 25th Pct | G12: =PERCENTILE(G4:G8,0.25) | H12: =PERCENTILE(H4:H8,0.25)
A13: 75th Pct | G13: =PERCENTILE(G4:G8,0.75) | H13: =PERCENTILE(H4:H8,0.75)
